fajrGPT/__init__.py
fajrGPT/quran_metadata.py
fajrGPT/utils.py
fajrGPT/wake.py
fajrGPT/assets/brown.mp3
fajrGPT/assets/noise/brown.mp3
fajrGPT/assets/noise/pink.mp3
fajrGPT/assets/prompt/allah_name_explanation.txt
fajrGPT/assets/prompt/first_verse_explanation.txt
fajrGPT/assets/prompt/telegraphic.txt
fajrGPT/assets/prompt/verse_explanation.txt
fajrGPT/assets/prompt/scholars/hamza_yusuf.txt
fajrGPT/assets/prompt/scholars/mufti_menk.txt
fajrGPT/assets/prompt/scholars/nouman_ali_khan.txt
fajrGPT-1.7.2.dist-info/LICENSE
fajrGPT-1.7.2.dist-info/METADATA
fajrGPT-1.7.2.dist-info/WHEEL
fajrGPT-1.7.2.dist-info/entry_points.txt
fajrGPT-1.7.2.dist-info/top_level.txt
fajrGPT-1.7.2.dist-info/RECORD
