Metadata-Version: 2.1
Name: fajrGPT
Version: 1.7.2
Summary: A Python application to assist in waking up for Fajr prayer by providing 3 interactive verses/explanations from the Quran + ChatGPT explanations accompanied by a soothing Islamic prayer fade-in and fade-out audio file from YouTube.
Home-page: https://github.com/malekinho8/quran-wake-up
Author: Malek Ibrahim
Author-email: shmeek8@gmail.com
Classifier: Development Status :: 3 - Alpha
Classifier: Topic :: Utilities
Classifier: License :: OSI Approved :: MIT License
Classifier: Programming Language :: Python :: 3.8
Requires-Python: >=3.8
License-File: LICENSE
Requires-Dist: click
Requires-Dist: pygame
Requires-Dist: pydub
Requires-Dist: moviepy
Requires-Dist: openai
Requires-Dist: tqdm
Requires-Dist: mutagen
Requires-Dist: scipy
Requires-Dist: TheQuranModule
